src/__init__.py
src/auto_rsa.py
src/brokerages/__init__.py
src/brokerages/bbae_api.py
src/brokerages/chase_api.py
src/brokerages/dspac_api.py
src/brokerages/fennel_api.py
src/brokerages/fidelity_api.py
src/brokerages/firstrade_api.py
src/brokerages/public_api.py
src/brokerages/robinhood_api.py
src/brokerages/schwab_api.py
src/brokerages/sofi_api.py
src/brokerages/tasty_api.py
src/brokerages/tornado_api.py
src/brokerages/tradier_api.py
src/brokerages/vanguard_api.py
src/brokerages/webull_api.py
src/brokerages/wellsfargo_api.py
src/brokers.py
src/cli.py
src/helper_api.py
src/vendors/robin_stocks/.git
src/vendors/robin_stocks/.github/workflows/pythonapp.yml
src/vendors/robin_stocks/.gitignore
src/vendors/robin_stocks/.readthedocs.yml
src/vendors/robin_stocks/.test.env
src/vendors/robin_stocks/LICENSE.txt
src/vendors/robin_stocks/MANIFEST.in
src/vendors/robin_stocks/README.rst
src/vendors/robin_stocks/Robinhood.rst
src/vendors/robin_stocks/contributing.md
src/vendors/robin_stocks/docs/Makefile
src/vendors/robin_stocks/docs/make.bat
src/vendors/robin_stocks/docs/source/_static/favicon.ico
src/vendors/robin_stocks/docs/source/_static/pics/gemini/create.png
src/vendors/robin_stocks/docs/source/_static/pics/gemini/final.png
src/vendors/robin_stocks/docs/source/_static/pics/gemini/market.png
src/vendors/robin_stocks/docs/source/_static/pics/gemini/primary.png
src/vendors/robin_stocks/docs/source/_static/pics/gemini/settings.png
src/vendors/robin_stocks/docs/source/_static/pics/robin.jpg
src/vendors/robin_stocks/docs/source/_static/pics/robinyell.jpg
src/vendors/robin_stocks/docs/source/_static/pics/tda/apps.png
src/vendors/robin_stocks/docs/source/_static/pics/tda/auth.png
src/vendors/robin_stocks/docs/source/_static/pics/tda/response.png
src/vendors/robin_stocks/docs/source/_static/pics/tda/url.png
src/vendors/robin_stocks/docs/source/_static/pics/title.PNG
src/vendors/robin_stocks/docs/source/_static/pics/two.jpg
auto_rsa_bot-2.0.1.dist-info/WHEEL
auto_rsa_bot-2.0.1.dist-info/entry_points.txt
auto_rsa_bot-2.0.1.dist-info/METADATA
auto_rsa_bot-2.0.1.dist-info/RECORD
