Metadata-Version: 2.3
Name: auto_rsa_bot
Version: 2.0.1
Requires-Dist: bbae-invest-api==0.1.3
Requires-Dist: chaseinvest-api==0.3.6
Requires-Dist: cryptography>=46.0.3
Requires-Dist: curl-cffi==0.13.0
Requires-Dist: discord-py==2.6.4
Requires-Dist: dspac-invest-api==0.1.3
Requires-Dist: email-validator>=2.3.0
Requires-Dist: fennel-invest-api==2.0.0
Requires-Dist: fidelity-api==0.0.16
Requires-Dist: firstrade==0.0.34
Requires-Dist: nodriver==0.48.1
Requires-Dist: paho-mqtt>=2.1.0
Requires-Dist: publicdotcom-py==0.1.3
Requires-Dist: pyotp==2.9.0
Requires-Dist: python-dotenv==1.2.1
Requires-Dist: requests==2.32.5
Requires-Dist: schwab-api2>=0.3.0
Requires-Dist: selenium-stealth==1.0.6
Requires-Dist: setuptools<81
Requires-Dist: tastytrade==9.11
Requires-Dist: typer>=0.20.0
Requires-Dist: vanguard-api==0.3.3
Requires-Python: >=3.12
